scuCourseDownloader/__init__.py
scuCourseDownloader/getColloge.py
scuCourseDownloader/main.py
scuCourseDownloader-0.0.2.dist-info/LICENSE
scuCourseDownloader-0.0.2.dist-info/METADATA
scuCourseDownloader-0.0.2.dist-info/WHEEL
scuCourseDownloader-0.0.2.dist-info/top_level.txt
scuCourseDownloader-0.0.2.dist-info/RECORD
