Metadata-Version: 2.1
Name: scuCourseDownloader
Version: 0.0.2
Summary: api to download scu courses
Home-page: https://github.com/2239559319/courseDownload
Author: 小川
Author-email: w2239559319@outlook.com
License: UNKNOWN
Platform: UNKNOWN
Classifier: Programming Language :: Python :: 3
Classifier: License :: OSI Approved :: Apache Software License
Classifier: Operating System :: OS Independent
